tinyspline-0.6.0.post2.data/purelib/tinyspline/__init__.py
tinyspline-0.6.0.post2.data/purelib/tinyspline/_tinysplinepython.so
tinyspline-0.6.0.post2.data/purelib/tinyspline/tinyspline.py
tinyspline-0.6.0.post2.dist-info/METADATA
tinyspline-0.6.0.post2.dist-info/WHEEL
tinyspline-0.6.0.post2.dist-info/top_level.txt
tinyspline-0.6.0.post2.dist-info/RECORD
