Metadata-Version: 2.1
Name: tinyspline
Version: 0.6.0.post2
Summary: Spline Library for a Multitude of Programming Languages
Home-page: https://github.com/msteinbeck/tinyspline
Author: Marcel Steinbeck
Author-email: tinyspline@retux.de
License: MIT
Platform: Windows
Classifier: Topic :: Scientific/Engineering :: Mathematics
Classifier: Topic :: Software Development :: Libraries :: Python Modules
Classifier: Programming Language :: Python
Classifier: License :: OSI Approved :: MIT License
